Workbook

Sheet Cover
B2: PERSONAL WEALTH PROFILE
B3: Comprehensive Financial Consolidation Report
B4: Satheesh Sivasubramonia Pillai | All amounts in INR (₹) | Exchange Rate: 309.3 INR/KD
B7: KEY FINANCIAL SUMMARY
B9: Total Assets | C9: Total Liabilities | D9: Net Worth | E9: Monthly Net Cash Flow | F9: Annual Net Cash Flow
B10: =Assets!D25 -> 39905750 | C10: =Liabilities!C15 -> 13640734 | D10: =B10-C10 -> 26265016 | E10: ='Cash Flow'!D22 -> 66206.083 | F10: ='Cash Flow'!E22 -> 794473
B12: PORTFOLIO HIGHLIGHTS
B14: Total Liquid & Financial Assets | E14: =Assets!D14 -> 18005750
B15: Total Real Estate Holdings | E15: =Assets!D23 -> 21900000
B16: Monthly Gross Income | E16: ='Income Statement'!D12 -> 391441.08
B17: Monthly Total Outflows | E17: ='Cash Flow'!D19 -> 325235
B18: Debt-to-Asset Ratio | E18: =C10/B10 -> 0.34182377
B19: Liquid Asset Coverage (months of expenses) | E19: =E14/E17 -> 55.362277
B22: REPORT INDEX
B24: Sheet Name | C24: Description
B25: Assets | C25: Detailed breakdown of all liquid, financial, and real estate assets (INR)
B26: Liabilities | C26: Complete liability schedule including loans and litigation exposure (INR)
B27: Balance Sheet | C27: Consolidated financial position — Assets, Liabilities & Net Worth
B28: Income Statement | C28: Monthly and annual income breakdown with FD interest included
B29: Cash Flow | C29: Monthly and annual inflows, outflows, and net cash flow analysis
B30: Dashboard | C30: Visual charts and KPIs for quick financial overview
B33: IMPORTANT NOTES
B35: • All Kuwait Dinar (KD) amounts converted to INR at 309.3 INR per 1 KD.
B36: • FD interest calculated at 7% p.a. (India) and 3.5% p.a. (Kuwait) — estimated market rates.
B37: • Under-construction flat (₹55 Lakhs paid) is under litigation — excluded from assets, included in liabilities as exposure.
B38: • Insurance premiums (Life, Health, Critical Illness) not included due to non-availability of premium amounts.
B39: • Endowment policy premium of ₹4 Lakhs/year included in annual expense analysis.
B40: • Net Worth = Total Assets − Total Liabilities. Litigation exposure treated as per user instruction.

Sheet Assets
B2: ASSET REGISTER
B3: All values in INR (₹) | Exchange Rate: 309.3 INR/KD
B5: A. LIQUID & FINANCIAL ASSETS
B6: Asset Description | C6: Original Amount | D6: INR Value | E6: % of Total | F6: Notes
B7: Fixed Deposit – Emergency Fund (India) | C7: Rs 10,00,000 | D7: 1000000 | E7: =D7/D25 -> 0.025059045 | F7: 7% p.a. interest
B8: Emergency Fund (Kuwait) | C8: KD 4,000 | D8: 1237200 | E8: =D8/D25 -> 0.031003051 | F8: Liquid cash reserve
B9: Fixed Deposit – Company Capital (Kuwait) | C9: KD 3,000 | D9: 927900 | E9: =D9/D25 -> 0.023252288 | F9: 3.5% p.a. interest
B10: Fixed Deposit – Son's CFA Studies (Kuwait) | C10: KD 3,000 | D10: 927900 | E10: =D10/D25 -> 0.023252288 | F10: 3.5% p.a. interest
B11: Savings Account – Investable Corpus (India) | C11: Rs 35,00,000 | D11: 3500000 | E11: =D11/D25 -> 0.087706659 | F11: To be deployed in MFs
B12: Loan Receivable (Kuwait) | C12: KD 17,500 | D12: 5412750 | E12: =D12/D25 -> 0.13563835 | F12: Expected this year
B13: Gold (in locker) | C13: Rs 50,00,000 | D13: 5000000 | E13: =D13/D25 -> 0.12529523 | F13: Physical gold holdings
B14: Subtotal – Liquid & Financial Assets | D14: =SUM(D7:D13) -> 18005750
B16: B. REAL ESTATE HOLDINGS
B17: Property | C17: Location / Status | D17: Estimated Value (INR) | E17: % of Total | F17: Income / Notes
B18: Residential Flat* | C18: India – Rented | D18: ='Income Statement'!F8 / 0.035 -> 8400000 | E18: =D18/D25 -> 0.21049598 | F18: Rs 24,500/month rental. Val calculated from 3.5% rental yield
B19: Plot 1 | C19: Trivandrum – Held | D19: 5000000 | E19: =D19/D25 -> 0.12529523 | F19: No income
B20: Plot 2 | C20: Trivandrum – Held | D20: 5000000 | E20: =D20/D25 -> 0.12529523 | F20: No income
B21: Plot 3 | C21: Bangalore – Held | D21: 3500000 | E21: =D21/D25 -> 0.087706659 | F21: No income
B22: Under-Construction Flat | C22: Litigation – EXCLUDED | D22: — | E22: — | F22: Rs 55L paid; not counted in assets per instruction
B23: Subtotal – Real Estate (Non-Litigation) | D23: =SUM(D18:D22) -> 21900000
B25: TOTAL ASSETS | D25: =D14+D23 -> 39905750

Sheet Liabilities
B2: LIABILITY SCHEDULE
B3: All values in INR (₹) | Exchange Rate: 309.3 INR/KD
B5: A. BORROWINGS & LOANS
B6: Liability | C6: Outstanding (INR) | D6: EMI (INR) | E6: Tenure Left | F6: Total Payable | G6: Lender / Notes
B7: Home Loan (India) | C7: 600000 | D7: 31400 | E7: ~1 year | F7: 376800 | G7: SBI
B8: Personal Loan (Kuwait) | C8: 7540734 | D8: 159289.5 | E8: ~4 years | F8: 7645896 | G8: Burgan Bank
B9: Subtotal – Loans | C9: =SUM(C7:C8) -> 8140734 | D9: =SUM(D7:D8) -> 190689.5 | F9: =SUM(F7:F8) -> 8022696
B11: B. LITIGATION-RELATED EXPOSURE
B12: Item | C12: Amount (INR) | D12: Status | E12: Expected Outcome | F12: Recovery | G12: Notes
B13: Flat Advance Paid (Under Litigation) | C13: 5500000 | D13: In litigation | E13: If won: flat + Rs 40L needed | F13: If lost: Rs 10-15L | G13: Rs 55L already paid; excluded from assets
B15: TOTAL LIABILITIES | C15: =C9+C13 -> 13640734 | D15: =D9 -> 190689.5

Sheet Balance Sheet
B2: CONSOLIDATED BALANCE SHEET
B3: As of June 2026 | All amounts in INR (₹) | Exchange Rate: 309.3 INR/KD
B5: ASSETS | E5: LIABILITIES
B7: LIQUID & FINANCIAL ASSETS | E7: BORROWINGS & LOANS
B8: Fixed Deposit – Emergency Fund | C8: =Assets!D7 -> 1000000 | E8: Home Loan – SBI (India) | F8: =Liabilities!C7 -> 600000
B9: Emergency Fund (Kuwait) | C9: =Assets!D8 -> 1237200 | E9: Personal Loan – Burgan Bank | F9: =Liabilities!C8 -> 7540734
B15: Subtotal – Liquid & Financial | C15: =SUM(C8:C14) -> 2237200 | E15: LITIGATION EXPOSURE
E16: Flat Advance Paid (Under Litigation) | F16: =Liabilities!C13 -> 5500000
E17: Subtotal – Litigation | F17: =F16 -> 5500000
E18: TOTAL LIABILITIES | F18: =SUM(F8:F9)+F16 -> 13640734
B19: REAL ESTATE HOLDINGS
B20: Residential Property | C20: =Assets!D18 -> 8400000 | E20: KEY METRICS
B21: Plot 1 – Trivandrum | C21: =Assets!D19 -> 5000000 | E21: Debt-to-Asset Ratio | F21: =F18/C26 -> 0.56513324
B22: Plot 2 – Trivandrum | C22: =Assets!D20 -> 5000000 | E22: Liquid Assets to Total Assets | F22: =C15/C26 -> 0.092686807
B23: Plot – Bangalore | C23: =Assets!D21 -> 3500000 | E23: Real Estate to Total Assets | F23: =C24/C26 -> 0.90731319
B24: Subtotal – Real Estate | C24: =SUM(C20:C23) -> 21900000 | E24: Net Worth Ratio | F24: =C28/C26 -> 0.43486676
B26: TOTAL ASSETS | C26: =C15+C24 -> 24137200
B28: NET WORTH (Assets – Liabilities) | C28: =C26-F18 -> 10496466

Sheet Income Statement
B2: INCOME STATEMENT
B3: Monthly & Annual | All amounts in INR (₹) | Exchange Rate: 309.3 INR/KD
B5: MONTHLY INCOME
B6: Income Source | C6: Original Amount | D6: Monthly (INR) | E6: % of Total | F6: Annual (INR) | G6: Notes
B7: Freelance Income (3 SME clients) | C7: KD 1,150 | D7: 355695 | E7: =D7/D12 -> 0.90868081 | F7: =D7*12 -> 4268340 | G7: Rs 40-45L/year range
B8: Rental Income – India Flat | C8: Rs 24,500 | D8: 24500 | E8: =D8/D12 -> 0.06258924 | F8: =D8*12 -> 294000 | G8: Including AMC
B9: FD Interest – India (7% p.a.) | C9: Rs 10L × 7% ÷ 12 | D9: 5833.3333 | E9: =D9/D12 -> 0.0149022 | F9: =D9*12 -> 70000 | G9: Estimated rate
B10: FD Interest – Company Capital (3.5% p.a.) | C10: KD 3K × 3.5% ÷ 12 | D10: 2706.375 | E10: =D10/D12 -> 0.0069138757 | F10: =D10*12 -> 32476.5 | G10: Estimated rate
B11: FD Interest – Son's CFA (3.5% p.a.) | C11: KD 3K × 3.5% ÷ 12 | D11: 2706.375 | E11: =D11/D12 -> 0.0069138757 | F11: =D11*12 -> 32476.5 | G11: Estimated rate
B12: TOTAL MONTHLY INCOME | D12: =SUM(D7:D11) -> 391441.08 | E12: 100% | F12: =SUM(F7:F11) -> 4697293
B14: ANNUAL EXPENSES (Non-EMI)
B15: Expense Item | D15: Annual Amount | F15: Monthly Equivalent | G15: Notes
B16: Endowment Policy Premium (Ageas Federal) | D16: 400000 | F16: =D16/12 -> 33333.333 | G16: Rs 4L/year, 2021-2027
B17: Life / Health / Critical Illness Premiums | D17: Not specified | G17: Metlife Life $320K, Niva Bupa Rs 1Cr, CI $150K
B19: INCOME SUMMARY
B20: Total Annual Gross Income | D20: =F12 -> 4697293
B21: Total Annual EMI Outflows | D21: =(515*309.3+31400)*12 -> 2288274
B22: Annual Household Expenses | D22: =435*309.3*12 -> 1614546 | F22: =Liabilities!D9*12 -> 2288274
B23: Annual Insurance Premium | D23: =D16 -> 400000 | F23: ='Cash Flow'!E17 -> 1614546
B24: Total Annual Outflows | D24: =(515*309.3+31400)*12+435*309.3*12+D16 -> 4302820
B25: NET ANNUAL SURPLUS (Income – Outflows) | D25: =F12-D24 -> 394473 | F25: =SUM(F22:F24) -> 3902820

Sheet Cash Flow
B2: CASH FLOW STATEMENT
B3: Monthly & Annual | All amounts in INR (₹) | Exchange Rate: 309.3 INR/KD
B5: MONTHLY CASH FLOW
B6: Item | C6: Original Amount | D6: Monthly (INR) | E6: Annual (INR) | F6: % of Annual Inflow | G6: Notes
B7: CASH INFLOWS
B8: Freelance Income | C8: KD 1,150 | D8: ='Income Statement'!D7 -> 355695 | E8: =D8*12 -> 4268340 | G8: 3 SME clients
B9: Rental Income – India Flat | C9: Rs 24,500 | D9: ='Income Statement'!D8 -> 24500 | E9: =D9*12 -> 294000 | G9: Including AMC
B10: FD Interest – India (7%) | C10: Rs 10L × 7% ÷ 12 | D10: ='Income Statement'!D9 -> 5833.3333 | E10: =D10*12 -> 70000 | G10: Estimated
B11: FD Interest – Co. Capital (3.5%) | C11: KD 3K × 3.5% ÷ 12 | D11: ='Income Statement'!D10 -> 2706.375 | E11: =D11*12 -> 32476.5 | G11: Kuwait FD
B12: FD Interest – Son's CFA (3.5%) | C12: KD 3K × 3.5% ÷ 12 | D12: ='Income Statement'!D11 -> 2706.375 | E12: =D12*12 -> 32476.5 | G12: Kuwait FD
B13: TOTAL INFLOWS | D13: =SUM(D8:D12) -> 391441.08 | E13: =SUM(E8:E12) -> 4697293
B15: CASH OUTFLOWS
B16: Personal Loan EMI (Burgan Bank) | C16: KD 515 | D16: =Liabilities!D8 -> 159289.5 | E16: =D16*12 -> 1911474 | G16: ~4 years remaining
B17: Household Expenses (Kuwait) | C17: KD 435 | D17: 134545.5 | E17: =D17*12 -> 1614546 | G17: Monthly living
B18: Home Loan EMI (SBI) | C18: Rs 31,400 | D18: =Liabilities!D7 -> 31400 | E18: =D18*12 -> 376800 | G18: ~1 year remaining
B19: TOTAL OUTFLOWS | D19: =SUM(D16:D18) -> 325235 | E19: =SUM(E16:E18) -> 3902820
B21: NET CASH FLOW
B22: Net Monthly Cash Flow | D22: =D13-D19 -> 66206.083 | E22: =E13-E19 -> 794473
B23: Savings Rate (Net / Inflow) | D23: =D22/D13 -> 0.16913422 | E23: =E22/E13 -> 0.16913422
B25: ANNUAL COMMITMENTS
B26: Endowment Policy Premium (Annual) | E26: ='Income Statement'!D16 -> 400000 | F26: Rs 4L/year, last payment 2027
B27: Total Annual Commitments (EMI + Household + Insurance) | E27: =E19+E26 -> 4302820
B28: Net Annual Cash Flow after All Commitments | E28: =E13-E27 -> 394473

Sheet Calc_Data
A1: Summary Metrics | D1: Asset Allocation | G1: Cash Inflows vs Outflows (Monthly) | K1: Liability Breakdown | W1: Property | X1: Value | Z1: Loan | AA1: EMI | AC1: Category | AD1: Amount | AF1: Asset | AG1: Value
A2: Metric | B2: Value | D2: Asset Type | E2: Value | G2: Category | H2: Inflow | I2: Outflow | K2: Liability | L2: Outstanding | N2: Income Source | O2: Amount | Q2: Expense Source | R2: Amount | T2: Asset Class | U2: Value | W2: =Assets!B17 -> Property | X2: =Assets!D17 -> Estimated Value (INR) | Z2: =Liabilities!B7 -> Home Loan (India) | AA2: =Liabilities!D7 -> 31400 | AC2: Annual Inflows | AD2: ='Cash Flow'!D13*12 -> 4697293 | AF2: =Assets!B7 -> Fixed Deposit – Emergency Fund (India) | AG2: =Assets!D7 -> 1000000
A3: Total Assets | B3: 39905750 | D3: Fixed Deposit – Emergency Fund (India) | E3: 1000000 | G3: Freelance Income | H3: 355695 | I3: 0 | K3: Home Loan (India) | L3: 600000 | N3: =IFERROR(__xludf.DUMMYFUNCTION("QUERY(G3:I10, ""SELECT G, H WHERE H > 0"", 0)"),"Freelance Income") -> Freelance Income | O3: =IFERROR(__xludf.DUMMYFUNCTION("""COMPUTED_VALUE"""),355695.0) -> 355695 | Q3: =IFERROR(__xludf.DUMMYFUNCTION("QUERY(G3:I10, ""SELECT G, I WHERE I > 0"", 0)"),"Personal Loan EMI") -> Personal Loan EMI | R3: =IFERROR(__xludf.DUMMYFUNCTION("""COMPUTED_VALUE"""),159290.0) -> 159290 | T3: Liquid & Financial Assets | U3: =SUM(E3:E9) -> 18005750 | W3: =Assets!B18 -> Residential Flat* | X3: =Assets!D18 -> 8400000 | Z3: =Liabilities!B8 -> Personal Loan (Kuwait) | AA3: =Liabilities!D8 -> 159289.5 | AC3: Annual Outflows | AD3: ='Cash Flow'!D19*12 -> 3902820 | AF3: =Assets!B8 -> Emergency Fund (Kuwait) | AG3: =Assets!D8 -> 1237200
A4: Total Liabilities | B4: 13640734 | D4: Emergency Fund (Kuwait) | E4: 1237200 | G4: Rental Income | H4: 24500 | I4: 0 | K4: Personal Loan (Kuwait) | L4: 7540734 | N4: =IFERROR(__xludf.DUMMYFUNCTION("""COMPUTED_VALUE"""),"Rental Income") -> Rental Income | O4: =IFERROR(__xludf.DUMMYFUNCTION("""COMPUTED_VALUE"""),24500.0) -> 24500 | Q4: =IFERROR(__xludf.DUMMYFUNCTION("""COMPUTED_VALUE"""),"Household Expenses") -> Household Expenses | R4: =IFERROR(__xludf.DUMMYFUNCTION("""COMPUTED_VALUE"""),134546.0) -> 134546 | T4: Real Estate Holdings | U4: =SUM(E10:E13) -> 21900000 | W4: =Assets!B19 -> Plot 1 | X4: =Assets!D19 -> 5000000 | AF4: =Assets!B9 -> Fixed Deposit – Company Capital (Kuwait) | AG4: =Assets!D9 -> 927900
A5: Net Worth | B5: 26265016 | D5: Fixed Deposit – Company Capital (Kuwait) | E5: 927900 | G5: FD Interest (India) | H5: 5833 | I5: 0 | N5: =IFERROR(__xludf.DUMMYFUNCTION("""COMPUTED_VALUE"""),"FD Interest (India)") -> FD Interest (India) | O5: =IFERROR(__xludf.DUMMYFUNCTION("""COMPUTED_VALUE"""),5833.0) -> 5833 | Q5: =IFERROR(__xludf.DUMMYFUNCTION("""COMPUTED_VALUE"""),"Home Loan EMI") -> Home Loan EMI | R5: =IFERROR(__xludf.DUMMYFUNCTION("""COMPUTED_VALUE"""),31400.0) -> 31400 | W5: =Assets!B20 -> Plot 2 | X5: =Assets!D20 -> 5000000 | AF5: =Assets!B10 -> Fixed Deposit – Son's CFA Studies (Kuwait) | AG5: =Assets!D10 -> 927900
A6: Monthly Net Cash Flow | B6: 66206 | D6: Fixed Deposit – Son's CFA Studies (Kuwait) | E6: 927900 | G6: FD Interest (Co. Capital) | H6: 2706 | I6: 0 | N6: =IFERROR(__xludf.DUMMYFUNCTION("""COMPUTED_VALUE"""),"FD Interest (Co. Capital)") -> FD Interest (Co. Capital) | O6: =IFERROR(__xludf.DUMMYFUNCTION("""COMPUTED_VALUE"""),2706.0) -> 2706 | AF6: =Assets!B11 -> Savings Account – Investable Corpus (India) | AG6: =Assets!D11 -> 3500000
A7: Annual Net Cash Flow | B7: 794473 | D7: Savings Account – Investable Corpus (India) | E7: 3500000 | G7: FD Interest (Son's CFA) | H7: 2706 | I7: 0 | N7: =IFERROR(__xludf.DUMMYFUNCTION("""COMPUTED_VALUE"""),"FD Interest (Son's CFA)") -> FD Interest (Son's CFA) | O7: =IFERROR(__xludf.DUMMYFUNCTION("""COMPUTED_VALUE"""),2706.0) -> 2706 | AF7: =Assets!B12 -> Loan Receivable (Kuwait) | AG7: =Assets!D12 -> 5412750
D8: Loan Receivable (Kuwait) | E8: 5412750 | G8: Personal Loan EMI | H8: 0 | I8: 159290 | AF8: =Assets!B13 -> Gold (in locker) | AG8: =Assets!D13 -> 5000000
D9: Gold (in locker) | E9: 5000000 | G9: Household Expenses | H9: 0 | I9: 134546
D10: Residential Flat (India) | E10: 8400000 | G10: Home Loan EMI | H10: 0 | I10: 31400
D11: Plot 1 (Trivandrum) | E11: 5000000
D12: Plot 2 (Trivandrum) | E12: 5000000
D13: Plot 3 (Bangalore) | E13: 3500000

Sheet Dashboard
B2: COMPREHENSIVE FINANCIAL DASHBOARD
